{
  "_comment": "Known drift: snapshots 0000/0001 predate CASCADE FKs (0002) and UNIQUE token_hash index (0002). drizzle-kit generate cannot run due to ESM .js extension resolution (MODULE_NOT_FOUND). Hand-written migrations 0002-0004 are source of truth.",
  "version": "7",
  "dialect": "postgresql",
  "entries": [
    {
      "idx": 0,
      "version": "7",
      "when": 1771943571017,
      "tag": "0000_thankful_smasher",
      "breakpoints": true
    },
    {
      "idx": 1,
      "version": "7",
      "when": 1772001304605,
      "tag": "0001_condemned_leader",
      "breakpoints": true
    },
    {
      "idx": 2,
      "version": "7",
      "when": 1772087400000,
      "tag": "0002_sprint0_hardening",
      "breakpoints": true
    },
    {
      "idx": 3,
      "version": "7",
      "when": 1772173800000,
      "tag": "0003_rls_tenant_isolation",
      "breakpoints": true
    },
    {
      "idx": 4,
      "version": "7",
      "when": 1772260200000,
      "tag": "0004_rls_hardening",
      "breakpoints": true
    },
    {
      "idx": 5,
      "version": "7",
      "when": 1772346600000,
      "tag": "0005_add_notnull_counters",
      "breakpoints": true
    },
    {
      "idx": 6,
      "version": "7",
      "when": 1772433000000,
      "tag": "0006_schema_alignment",
      "breakpoints": true
    }
  ]
}
